{"patient_id": 92343, "patient_uid": "2763772-1", "PMID": 19882032, "file_path": "comm/PMC002xxxxxx/PMC2763772.xml", "title": "INFANTILE IATROGENIC CUSHING'S SYNDROME", "patient": "A 6-month-old male child was admitted to our hospital with a 3-month history of overweight. His family history revealed that he is the third living child. He had two healthy brothers, aged four and seven. His brothers and other members of the family had no similar disease.\\nOn physical examination, axillary temperature was 37\u00b0C, blood pressure was 111/68 mmHg and heart rate was 98/min. His weight was 8600 g 75\u201390th percentile, height 65 cm 25\u201350th percentile, and head circumference 42 cm 10\u201325th percentile. He had Cushingoid image, truncal obesity, drumstick limbs, and paper-thin skin with striae, and crops of dense, inflamed pustules on his chest and back ().\\nOn laboratory examination \u2013 hemoglobin: 14.6 g/dl, white blood cell: 16,600/mm3, platelet: 614,000/mm3, serum glucose: 91 mg/dl, blood urea: 25 mg/dl, creatinine: 0.4 mg/dl, sodium: 142 mEq/L, potassium: 4 mEq/L, chloride: 105 mEq/L.\\nMorning cortisol level was low, 0.66 \u03bcg/dl. Adrenocorticotropic hormone (ACTH) was not elevated, 7.1 pg/ml. The peak cortisol level after the standard dose of 250 \u03bcg/m2 ACTH was 18.2 \u03bcg/dl.\\nWhen parents were questioned for the details of patient's history, we learned about the usage of pomade clobetasol-17-propionate (3 tubes, each of 30g). It was used two to three times in a day for the last 3 months for skin dryness. This product was purchased from drugstore without any prescription. The parents were not informed about the application period and possible side effects of the product.", "age": "[[6.0, 'month']]", "gender": "M", "relevant_articles": "{'11926057': 1, '11836801': 1, '20972726': 1, '29379569': 2, '30274478': 1, '10742322': 1, '15461763': 1, '26288430': 2, '11306142': 1, '19882032': 2}", "similar_patients": "{'5760680-1': 1, '4533560-1': 1}"}