{"patient_id": 123808, "patient_uid": "5890000-2", "PMID": 29611410, "file_path": "noncomm/PMC005xxxxxx/PMC5890000.xml", "title": "Total Transcanal Endoscopic Facial Nerve Decompression for Traumatic Facial Nerve Palsy", "patient": "A 39-year-old male who experienced head trauma after falling down 10 days before he visited our clinic with left facial palsy and bilateral hearing impairment. HRCT scan showed fracture line crossed left tympanic segment of facial nerve, and audiological evaluation showed bilateral hearing loss ().\\nThe patient underwent facial nerve decompression from the GG to the second genu by endoscopic transcanal approach. Then, ossiculoplasty was done. Six months after the operation, the patient showed hearing improvement at low frequencies (), and facial nerve function improved from H-B grade V to III (). This slow recovery was due to difference in degree of injury and personal vulnerability.", "age": "[[39.0, 'year']]", "gender": "M", "relevant_articles": "{'27468633': 1, '21671230': 1, '11458219': 1, '20564723': 1, '24665853': 1, '27593878': 1, '15991088': 1, '22182890': 1, '22468244': 1, '28302380': 1, '31569311': 1, '23010794': 1, '29611410': 2}", "similar_patients": "{'5890000-1': 2}"}